Metadata-Version: 2.0
Name: odoo10-addon-account-due-list
Version: 10.0.2.0.0
Summary: Payments Due list
Home-page: http://www.agilebg.com
Author: Odoo Community Association (OCA), Agile Business Group, Tecnativa,Zikzakmedia SL
Author-email: support@odoo-community.org
License: AGPL-3
Platform: UNKNOWN
Classifier: Programming Language :: Python
Classifier: Framework :: Odoo
Classifier: License :: OSI Approved :: GNU Affero General Public License v3
Requires-Python: ~=2.7
Requires-Dist: odoo (<10.1dev,>=10.0)
